{
  "game": "明日方舟",
  "source": "https://ak-webview.hypergryph.com/api/game/bulletinList?target=Android",
  "fetchedAt": "2026-07-15T00:19:42.303897+08:00",
  "timezone": "Asia/Shanghai",
  "count": 6,
  "notes": [
    "7590 跳过：沉沦者的黑流树 海主题官网",
    "6783 解析寻访「确定性混沌」时段",
    "6783 采用关卡开放时间",
    "4858 通讯正文 1027 字",
    "4858 模糊预告：红丝绒 7月中下旬",
    "4858 预告已过期：丛林症结 7月上旬",
    "2087 跳过：生息演算 使用声明",
    "2037 跳过：个人信息保护 双清单查询指引",
    "7738 跳过：《明日方舟》 公平运营申明",
    "5604 寻访「确定性混沌」对齐长公告时段",
    "8229 寻访「中坚寻访」用展示日估时",
    "2949 寻访「常驻标准寻访」用展示日估时"
  ],
  "analysis": {
    "method": "官方游戏内公告 API + 正则抽取活动时间段",
    "detailApi": "https://ak-webview.hypergryph.com/api/game/bulletin/{cid}",
    "tips": [
      "长公告（如「活动即将开启」）常含多段时间：关卡/兑换/寻访分别解析",
      "寻访纯图公告用海报；时段优先对齐活动长公告里的「【池名】限时寻访」",
      "中坚/标准等无展示日估时（约两周），有长公告则覆盖",
      "进度条按主时段（优先「活动时间/关卡开放/寻访」）计算已过比例"
    ]
  },
  "events": [
    {
      "id": "2949",
      "title": "常驻标准寻访 限时出率上升",
      "header": "「常驻标准寻访」限时寻访",
      "type": "寻访",
      "banner": "./covers/gacha-2949.png",
      "link": "uniwebview://move?target=recruit&param1=DOUBLE_74_0_6",
      "updatedAt": "2026-06-30T18:22:13+08:00",
      "primaryLabel": "估时（纯图公告）",
      "allRanges": [
        {
          "label": "估时（纯图公告）",
          "start": "2026-07-02T16:00:00+08:00",
          "end": "2026-07-16T03:59:00+08:00",
          "raw": "displayTime=2026-07-02"
        }
      ],
      "summary": "卡池「常驻标准寻访」",
      "textPreview": "",
      "start": "2026-07-02T16:00:00+08:00",
      "end": "2026-07-16T03:59:00+08:00",
      "status": "进行中",
      "remain": "剩1天3时",
      "progress": 91.5,
      "days": {
        "elapsedDays": 12.3,
        "remainDays": 1.2,
        "totalDays": 13.5
      },
      "hasSchedule": true,
      "kind": "live",
      "bannerRemote": "https://web.hycdn.cn/announce/images/20260630/fb473a22ea30dd0a51f1020ed6ace94c.png",
      "playable": false,
      "category": "gacha",
      "fuzzy": true
    },
    {
      "id": "6783",
      "title": "【丛林症结】 活动即将开启",
      "header": "故事集「丛林症结」限时活动即将开启",
      "type": "活动",
      "banner": "./covers/6783.png",
      "link": "https://ak.hypergryph.com/",
      "updatedAt": "2026-07-06T17:38:30+08:00",
      "primaryLabel": "关卡开放时间",
      "allRanges": [
        {
          "label": "关卡开放时间",
          "start": "2026-07-10T12:00:00+08:00",
          "end": "2026-07-17T03:59:00+08:00",
          "raw": " 关卡开放时间： 07月10日 12:00 - 07月17日 03:59"
        },
        {
          "label": "【全息修复仪】兑换时间",
          "start": "2026-07-10T12:00:00+08:00",
          "end": "2026-07-20T03:59:00+08:00",
          "raw": " 【全息修复仪】兑换时间： 07月10日 12:00 - 07月20日 03:59"
        },
        {
          "label": "活动时间",
          "start": "2026-07-10T12:00:00+08:00",
          "end": "2026-07-24T03:59:00+08:00",
          "raw": " 活动时间： 07月10日 12:00 - 07月24日 03:59"
        },
        {
          "label": "售卖时间",
          "start": "2026-07-10T12:00:00+08:00",
          "end": "2026-07-23T23:59:00+08:00",
          "raw": " 售卖时间： 07月10日 12:00 - 07月23日 23:59"
        },
        {
          "label": "售卖时间",
          "start": "2026-07-10T12:00:00+08:00",
          "end": "2026-07-31T03:59:00+08:00",
          "raw": " 售卖时间： 07月10日 12:00 - 07月31日 03:59"
        }
      ],
      "summary": "",
      "textPreview": "一、故事集「丛林症结」限时开启 \n 关卡开放时间： 07月10日 12:00 - 07月17日 03:59\n 关卡解锁条件： 通关主线1-10\n 关卡掉落： 猎犬食糜、素材等\n 活动说明： 活动期间将限时开放「丛林症结」活动关卡，玩家可通过活动作战收集「猎犬食糜」后在【全息修复仪】中兑换活动奖励及事相碎片，事相碎片可用于当期及往期故事集的剧情解锁\n \n ◆本次活动开启时间存在提前或延迟的可能，详情请关注后续公告\n \n 【全息修复仪】兑换时间： 07月10日 12:00 - 07月20日 03:59\n 【全息修复仪】兑换奖励： 时装【珊瑚海岸系列 - 悠然假日 HDm25 - 隐现】 、 事相碎片 、模组养成材料、高级养成素材、作战记录、龙门币、招聘许可等\n \n 注意： \n ◆本次活动结束后该故事集将收录至【情报处理室】中\n \n 二、【确定性混沌】限时寻访开启 \n 活动时间： 07月10日 12:00 - 07月24日 03:59\n 活动说明： 活动期间【确定性混沌】限时寻访开启，该寻访中以下干员出现率上升\n ★★★★★★：谬因（占6★出率的50%） \n ★★★★★： 佩德洛 / 钼铅（占5★出率的50%） \n \n 注意： \n ◆本次活动【确定性混沌】寻访为【标准寻访】，如果连续150次没有获得该限时寻访中出率上升的六星干员，则下一次招募到的六星干员必定为该限时寻访中出率上升的六星干员\n \n 三、新干员登场，信赖获取提升 \n 新增干员： 以下新增干员除加入【确定性混沌】寻访外，将在07月16日04:00后加入并常驻其余【标准寻访】卡池\n ★★★★★★：谬因 \n ★★★★★： 佩德洛 \n \n 注意： \n ◆本次活动关卡开放期间以上新增干员信赖获取提升\n \n 四、「全息作战矩阵」重构批次#2开放 \n 开放时间： 07月10日 12:00\n 解锁条件： 通关主线H5-1或H9-1或H15-1\n 活动说明： 「全息作战矩阵」重构批次#2开放，该玩法内的关卡设置有不同的追加指标，玩家可自由选择指标进行作战，达成指定条件后可获取主题场景、活动饰牌奖励\n \n 五、基建适配表情套组 \n 更新时间： 07月10日 12:00\n 更新说明： 07月10日 12:00版本更新后，基建的行动模式下可以使用已拥有的表情套组，会客室的留言板也将支持展示表情\n \n 六、新装限时上架 \n 活动时间： 07月10日 12:00 - 07月24日 03:59\n 活动说明： 活动期间以下干员新增时装将在时装商店上架并限时贩售：\n ◆【珊瑚海岸】系列 - 夏卉 FA098 - 莱伊 \n ◆【珊瑚海岸】系列 - 夏卉 FA240 - 陨星 \n ◆【珊瑚海岸】系列 - 悠然假日 HD59 - 卡达 \n \n ◆【音律联觉】系列 - 曙光祝颂 - 圣聆初雪 \n \n 七、复刻时装限时上架 \n 活动时间： 07月10日 12:00 - 07月24日 03:59\n 活动说明： 活动期间以下干员时装将在时装商店上架并限时贩售：\n ◆【珊瑚海岸】系列 - 夏卉 FA137 - 林 \n ◆【0011/韵】系列 - 行梦侧畔 - 鸿雪 \n ◆【0011/韵】系列 - 与荷 - 蛇屠箱 \n \n ◆【珊瑚海岸】系列 - 夏卉 FA075 - 焰影苇草 \n ◆【珊瑚海岸】系列 - 温差 RT.RX07 - 提丰 \n ◆【珊瑚海岸】系列 - 悠然假日 HD78 - 但书 \n ◆【珊瑚海岸】系列 - 灿阳朝露 SDm09 - 铅踝 \n \n ◆【命途迭代】系列 - 趋光之暗 - 阿斯卡纶 \n ◆【时代】系列 - 注目深渊 - 乌尔比安 \n \n ◆【时代】系列 - 翻涌 - 海霓 \n ◆【时代】系列 - 搁浅 - 海沫 \n ◆时装回顾展IV \n \n 注意： \n ◆时装回顾展使用合成玉参与，参与后可随机获得指定范围内的一",
      "start": "2026-07-10T12:00:00+08:00",
      "end": "2026-07-17T03:59:00+08:00",
      "status": "进行中",
      "remain": "剩2天3时",
      "progress": 67.7,
      "days": {
        "elapsedDays": 4.5,
        "remainDays": 2.2,
        "totalDays": 6.7
      },
      "hasSchedule": true,
      "kind": "live",
      "bannerRemote": "https://web.hycdn.cn/announce/images/20260702/409801207bc9ffeca7b0240b7cbe82ef.png",
      "playable": true,
      "category": "combat"
    },
    {
      "id": "8229",
      "title": "中坚寻访 干员出率上升",
      "header": "「中坚寻访」限时寻访",
      "type": "寻访",
      "banner": "./covers/gacha-8229.jpg",
      "link": "uniwebview://move?target=recruit&param1=CLASSIC_DOUBLE_74_0_3",
      "updatedAt": "2026-07-09T03:10:14+08:00",
      "primaryLabel": "估时（纯图公告）",
      "allRanges": [
        {
          "label": "估时（纯图公告）",
          "start": "2026-07-09T16:00:00+08:00",
          "end": "2026-07-23T03:59:00+08:00",
          "raw": "displayTime=2026-07-09"
        }
      ],
      "summary": "卡池「中坚寻访」",
      "textPreview": "",
      "start": "2026-07-09T16:00:00+08:00",
      "end": "2026-07-23T03:59:00+08:00",
      "status": "进行中",
      "remain": "剩8天3时",
      "progress": 39.6,
      "days": {
        "elapsedDays": 5.3,
        "remainDays": 8.2,
        "totalDays": 13.5
      },
      "hasSchedule": true,
      "kind": "live",
      "bannerRemote": "https://web.hycdn.cn/announce/images/20260709/95bcf5ba3d04a8047d98b9409f57723b.jpg",
      "playable": false,
      "category": "gacha",
      "fuzzy": true
    },
    {
      "id": "5604",
      "title": "【确定性混沌】 限时寻访开启",
      "header": "「确定性混沌」限时寻访",
      "type": "寻访",
      "banner": "./covers/gacha-5604.png",
      "link": "uniwebview://move?target=recruit&param1=SINGLE_75_0_1",
      "updatedAt": "2026-07-09T14:27:54+08:00",
      "primaryLabel": "活动时间·寻访",
      "allRanges": [
        {
          "label": "活动时间·寻访",
          "start": "2026-07-10T12:00:00+08:00",
          "end": "2026-07-24T03:59:00+08:00",
          "raw": "【确定性混沌】限时寻访开启 活动时间： 07月10日 12:00 - 07月24日 03:59"
        }
      ],
      "summary": "卡池「确定性混沌」",
      "textPreview": "",
      "start": "2026-07-10T12:00:00+08:00",
      "end": "2026-07-24T03:59:00+08:00",
      "status": "进行中",
      "remain": "剩9天3时",
      "progress": 33.0,
      "days": {
        "elapsedDays": 4.5,
        "remainDays": 9.2,
        "totalDays": 13.7
      },
      "hasSchedule": true,
      "kind": "live",
      "bannerRemote": "https://web.hycdn.cn/announce/images/20260709/9044b0db55caaebc3cea3446da96f321.png",
      "playable": false,
      "category": "gacha",
      "fuzzy": false
    },
    {
      "id": "4858-f0",
      "title": "预告·红丝绒",
      "header": "「红丝绒」预计7月中下旬开启",
      "type": "活动",
      "banner": "./covers/event-80b932579c.jpg",
      "link": "https://ak.hypergryph.com/",
      "updatedAt": "2026-06-18T17:02:26+08:00",
      "primaryLabel": "7月中下旬（估）",
      "allRanges": [
        {
          "label": "7月中下旬（估）",
          "start": "2026-07-21T16:00:00+08:00",
          "end": "2026-07-29T16:00:00+08:00",
          "raw": "SideStory「红丝绒」复刻活动将于7月中下旬"
        }
      ],
      "summary": "",
      "textPreview": "感谢大家一直以来对《明日方舟》的关注与支持，很高兴和大家再次见面。在本期制作组通讯发布之际，危机合约#5「涤墨作战」即将开启，欢迎大家体验，同时也再次感谢大家对于此前SideStory「泡影苍霆」的喜爱与支持。\n \n 以下，则是本次制作组通讯为大家带来的最新一期的相关活动及版本内容：\n \n 【通讯节点·一】 \n ●【明日方舟×小马宝莉】魔法与友谊合作活动将于7月上旬开启，活动期间玩家达成指定条件可获得活动家具等奖励，联动系列时装、头像等联动内容将同步上架贩售。\n \n 【通讯节点·二】 \n ●在玻利瓦尔，人们一次又一次经历相同的故事。\n 不同的疾病，在被切开的血管里蔓延。\n 穿越种植园的铁轨震颤着，发出一声声恸哭。\n 孩子们捡起土地的碎片，试图拼凑出母亲的模样。\n \n ●故事集「丛林症结」限时活动将于7月上旬开启，该活动除包含全新活动关卡与剧情外，新干员、新时装以及相关主题家具也将伴随本次活动登场及上架。\n \n 【通讯节点·三】 \n ●【全息作战矩阵】 重构批次#2将于7月上旬开启，本次更新将新增作战关卡，还会增设全新家具饰牌和主题场景奖励。\n \n 【通讯节点·四】 \n ●【集成战略】全新主题将于7月中旬开启，更多玩法介绍请关注后续官方自媒体相关介绍。\n \n 【通讯节点·五】 \n ●SideStory「红丝绒」复刻活动将于7月中下旬开启，【永不落幕】限时寻访将同期进行复刻，该活动同期上架的家具也将限时复刻。此外，还将有【时代】系列全新时装在本次复刻活动中上架贩售。\n \n 注意：\n 本次复刻活动关卡将继承玩家此前的活动关卡进度及首次掉落进度；\n 本次复刻活动结束后该活动关卡将常驻至【曲谱】；\n 本次复刻活动中部分无法重复获得的活动奖励将在重复获得时按照对应比例兑换为【情报凭证】，【情报凭证】兑换比例可参照活动中相应【情报凭证转换规则】；\n 【情报凭证】商店内物品将在活动开启时在原有的商品数量上进行叠加补货及新增其他商品。\n \n 最后，感谢大家阅读本期制作组通讯，以下为本次的制作组通讯奖励：\n \n 奖励内容： 合成玉*200、环烃聚质*5\n 发放时间： 06月23日17:00（邮件领取有效期：7日）\n 发放范围： 06月23日17:00前所有注册并创建角色的玩家\n \n \n *制作组通讯并不代表版本更新及活动最终内容，详细活动计划与版本更新内容等请以届时相关公告为准*\n \n \n \n 《明日方舟》制作组\n 2026年06月23日",
      "start": "2026-07-21T16:00:00+08:00",
      "end": "2026-07-29T16:00:00+08:00",
      "status": "即将开始",
      "remain": "6天后",
      "progress": 0.0,
      "days": {
        "elapsedDays": 0,
        "remainDays": 6.7,
        "totalDays": 8.0,
        "untilStartDays": 6.7
      },
      "hasSchedule": true,
      "kind": "preview",
      "playable": true,
      "category": "combat",
      "fuzzy": true
    },
    {
      "id": "6784",
      "title": "小马宝莉 联动即将开启",
      "header": "【明日方舟×小马宝莉】魔法与友谊合作活动即将开启",
      "type": "活动",
      "banner": "./covers/6784.png",
      "link": "https://ak.hypergryph.com/",
      "updatedAt": "2026-07-02T11:19:04+08:00",
      "primaryLabel": "活动时间",
      "allRanges": [
        {
          "label": "活动时间",
          "start": "2026-07-03T16:00:00+08:00",
          "end": "2026-07-13T03:59:00+08:00",
          "raw": " 活动时间： 07月03日 16:00 - 07月13日 03:59"
        },
        {
          "label": "活动时间",
          "start": "2026-07-03T16:00:00+08:00",
          "end": "2026-07-24T03:59:00+08:00",
          "raw": " 活动时间： 07月03日 16:00 - 07月24日 03:59"
        }
      ],
      "summary": "",
      "textPreview": "一、【明日方舟×小马宝莉】，魔法与友谊合作活动开启 \n 活动时间： 07月03日 16:00 - 07月13日 03:59\n 活动说明： 活动期间内，全平台PV播放量达到特定值可解锁活动家具、养成素材等奖励\n \n 二、【明日方舟×小马宝莉】，组合包限时上架 \n 活动时间： 07月03日 16:00 - 07月24日 03:59\n 活动说明： 活动期间，采购中心将限时售卖以下组合包\n \n [魔法护卫组合包] \n 组合包内容： 合成玉*400、 头像“赤沙娜仁图亚”*1、头像“不言弃的格拉尼”*1、头像“林间流星”*1、头像“空中大爆破”*1 \n \n [友谊骑士组合包] \n 组合包内容： 合成玉*400、 头像“坚忍玛恩纳”*1、头像“灼灼临光”*1、头像“瑕光点点”*1、头像“鞭刃佐菲娅”*1 \n \n [真挚友谊组合包] \n 组合包内容： 至纯源石*10、合成玉*2000、主题场景 「金橡树图书馆」*1 、名片主题 「合照」*1 、播放器 「碧琪的音乐播放器」*1 \n \n ◆名片主题「合照」可切换不同样式并使用：娜仁图亚、林、瑕光\n \n 三、【明日方舟×小马宝莉】，新装限时上架 \n 活动时间： 07月03日 16:00 - 07月24日 03:59\n 活动说明： 活动期间以下干员新增时装将在时装商店上架并限时贩售\n ◆【CROSSOVER】系列 - 善良坚强之心 - 瑕光 \n ◆【CROSSOVER】系列 - 求知的魔法 - 林 \n ◆【CROSSOVER】系列 - 率直诚实之人 - 娜仁图亚 \n \n 注意： \n ◆以上【明日方舟×小马宝莉】时装不可使用【时装自选凭证】道具兑换 \n \n \n 更多活动内容请持续关注《明日方舟》游戏内公告及官方公告。\n \n \n 【明日方舟】运营组\n 2026年06月28日",
      "start": "2026-07-03T16:00:00+08:00",
      "end": "2026-07-13T03:59:00+08:00",
      "status": "已结束",
      "remain": "已结束",
      "progress": 100.0,
      "days": {
        "elapsedDays": 9.5,
        "remainDays": 0,
        "totalDays": 9.5
      },
      "hasSchedule": true,
      "kind": "done",
      "bannerRemote": "https://web.hycdn.cn/announce/images/20260625/64f59feb22ef9770a194832aa57f1ceb.png",
      "playable": true,
      "category": "combat"
    }
  ]
}